[
    {
      "id": 1,
      "title": "A Study on Human-Robot Interaction",
      "author": "Haoyan Li and John Doe",
      "year": 2023,
      "journal": "International Journal of Robotics",
      "volume": "42",
      "number": "3",
      "pages": "123-145",
      "month": "mar",
      "doi": "10.1234/hri.2023.001",
      "abstract": "This paper explores the design environment for rapid prototyping of HRI applications using tinkered soft robots.",
      "keywords": ["HRI", "soft robotics", "UI/UX"],
      "url": "https://example.com/publication/1",
      "publisher": "Springer",
      "address": "Berlin, Germany",
      "booktitle": "Proceedings of the International Conference on Robotics",
      "editor": "Jane Smith and Alice Johnson",
      "series": "Lecture Notes in Computer Science",
      "edition": "1st",
      "organization": "Robotics Society",
      "note": "Invited paper",
      "type": "article"
    },
    {
      "id": 2,
      "title": "Teleoperation UI for Soft Robots",
      "author": "Haoyan Li",
      "year": 2024,
      "journal": "Journal of Robotics and Automation",
      "volume": "15",
      "number": "1",
      "pages": "55-70",
      "month": "jan",
      "doi": "10.1234/teleop.2024.002",
      "abstract": "The paper presents a novel solution for teleoperation UI problems in soft robotics.",
      "keywords": ["teleoperation", "soft robotics"],
      "url": "https://example.com/publication/2",
      "publisher": "IEEE",
      "address": "New York, USA",
      "booktitle": "Proceedings of the IEEE Conference on Robotics",
      "editor": "Michael Brown",
      "series": "IEEE Robotics Series",
      "edition": "2nd",
      "organization": "IEEE Robotics and Automation Society",
      "note": "Best paper award",
      "type": "conference"
    },
    {
      "id": 3,
      "title": "Advancements in Soft Robotics Materials",
      "author": "Haoyan Li, Sarah Johnson, and Robert Chen",
      "year": 2022,
      "journal": "Advanced Materials for Robotics",
      "volume": "8",
      "number": "4",
      "pages": "201-220",
      "month": "apr",
      "doi": "10.1234/amr.2022.003",
      "abstract": "This review paper discusses recent advancements in materials used for soft robotics, focusing on their properties and applications.",
      "keywords": ["soft robotics", "materials science", "flexible electronics"],
      "url": "https://example.com/publication/3",
      "publisher": "Wiley",
      "address": "Hoboken, USA",
      "booktitle": "Annual Review of Robotics Materials",
      "editor": "Emily White",
      "series": "Materials in Robotics",
      "edition": "3rd",
      "organization": "International Society for Robotics Materials",
      "note": "Highly cited paper",
      "type": "review"
    },
    {
      "id": 4,
      "title": "Machine Learning Approaches in Soft Robotics Control",
      "author": "Haoyan Li and Alex Turner",
      "year": 2023,
      "journal": "Artificial Intelligence in Robotics",
      "volume": "12",
      "number": "2",
      "pages": "78-95",
      "month": "feb",
      "doi": "10.1234/air.2023.004",
      "abstract": "This paper explores various machine learning techniques for improving control systems in soft robotics.",
      "keywords": ["machine learning", "soft robotics", "control systems"],
      "url": "https://example.com/publication/4",
      "publisher": "ACM",
      "address": "New York, USA",
      "booktitle": "Proceedings of the International Conference on AI in Robotics",
      "editor": "David Lee and Sophia Garcia",
      "series": "ACM International Conference Proceedings Series",
      "edition": "1st",
      "organization": "Association for Computing Machinery",
      "note": "Selected for oral presentation",
      "type": "conference"
    },
    {
      "id": 5,
      "title": "Ethical Considerations in Human-Robot Interaction Design",
      "author": "Haoyan Li, Emma Davis, and Chris Wilson",
      "year": 2024,
      "journal": "Ethics in Technology",
      "volume": "18",
      "number": "3",
      "pages": "300-315",
      "month": "mar",
      "doi": "10.1234/et.2024.005",
      "abstract": "This paper discusses the ethical implications and considerations in designing human-robot interaction systems, with a focus on soft robotics applications.",
      "keywords": ["ethics", "HRI", "soft robotics", "design principles"],
      "url": "https://example.com/publication/5",
      "publisher": "Oxford University Press",
      "address": "Oxford, UK",
      "booktitle": "Handbook of Ethics in Robotics and AI",
      "editor": "Patricia Brown",
      "series": "Oxford Handbooks in Technology Ethics",
      "edition": "2nd",
      "organization": "International Association for Technology Ethics",
      "note": "Interdisciplinary research",
      "type": "book chapter"
    },
    {
      "id": 6,
      "title": "Soft Robotics in Medical Applications",
      "author": "Haoyan Li, Maria Rodriguez, and Thomas Wang",
      "year": 2022,
      "journal": "Journal of Medical Robotics",
      "volume": "5",
      "number": "2",
      "pages": "45-60",
      "month": "jun",
      "doi": "10.1234/jmr.2022.006",
      "abstract": "This paper explores the potential applications of soft robotics in various medical fields, including surgery and rehabilitation.",
      "keywords": ["soft robotics", "medical robotics", "healthcare"],
      "url": "https://example.com/publication/6",
      "publisher": "Elsevier",
      "address": "Amsterdam, Netherlands",
      "booktitle": "Advances in Medical Robotics",
      "editor": "Jennifer Lee",
      "series": "Medical Technology Series",
      "edition": "1st",
      "organization": "International Society for Medical Robotics",
      "note": "Featured in journal's highlights",
      "type": "article"
    },
    {
      "id": 7,
      "title": "Biomimetic Design Principles in Soft Robotics",
      "author": "Haoyan Li and Oliver Green",
      "year": 2023,
      "journal": "Nature Robotics",
      "volume": "8",
      "number": "5",
      "pages": "220-235",
      "month": "may",
      "doi": "10.1234/nr.2023.007",
      "abstract": "This review article discusses how principles from nature are applied in the design of soft robots, enhancing their functionality and adaptability.",
      "keywords": ["biomimetics", "soft robotics", "nature-inspired design"],
      "url": "https://example.com/publication/7",
      "publisher": "Nature Publishing Group",
      "address": "London, UK",
      "booktitle": "Annual Review of Robotics",
      "editor": "Sarah Thompson",
      "series": "Nature Reviews",
      "edition": "2023",
      "organization": "Royal Society of Robotics",
      "note": "Cover feature",
      "type": "review"
    },
    {
      "id": 8,
      "title": "Energy-Efficient Actuation in Soft Robots",
      "author": "Haoyan Li, Kevin Zhang, and Laura Martinez",
      "year": 2024,
      "booktitle": "Proceedings of the International Conference on Soft Robotics",
      "pages": "78-85",
      "month": "aug",
      "doi": "10.1234/icsr.2024.008",
      "abstract": "This conference paper presents novel approaches to improve energy efficiency in soft robot actuation systems.",
      "keywords": ["soft robotics", "energy efficiency", "actuation"],
      "url": "https://example.com/publication/8",
      "publisher": "IEEE",
      "address": "San Francisco, USA",
      "editor": "Robert Johnson and Emily Chen",
      "series": "IEEE Xplore",
      "organization": "IEEE Robotics and Automation Society",
      "note": "Best poster award",
      "type": "conference"
    },
    {
      "id": 9,
      "title": "Soft Robotics: Principles and Future Directions",
      "author": "Haoyan Li",
      "year": 2025,
      "publisher": "Cambridge University Press",
      "address": "Cambridge, UK",
      "isbn": "978-1-234-56789-0",
      "abstract": "This comprehensive textbook covers the fundamental principles of soft robotics and explores potential future developments in the field.",
      "keywords": ["soft robotics", "robotics education", "future technologies"],
      "url": "https://example.com/publication/9",
      "edition": "1st",
      "series": "Emerging Technologies in Robotics",
      "note": "Adopted by multiple universities",
      "type": "book"
    },
    {
      "id": 10,
      "title": "Soft Robotic Interfaces for Human Augmentation",
      "author": "Haoyan Li, Yuki Tanaka, and Daniel Brown",
      "year": 2023,
      "journal": "Wearable Technologies",
      "volume": "7",
      "number": "4",
      "pages": "180-195",
      "month": "oct",
      "doi": "10.1234/wt.2023.010",
      "abstract": "This article explores the use of soft robotic technologies in creating wearable devices for human augmentation and assistance.",
      "keywords": ["soft robotics", "wearable technology", "human augmentation"],
      "url": "https://example.com/publication/10",
      "publisher": "IOP Publishing",
      "address": "Bristol, UK",
      "booktitle": "Advances in Wearable Robotics",
      "editor": "Lisa Anderson",
      "series": "IOP Conference Series",
      "edition": "2023",
      "organization": "International Wearable Robotics Association",
      "note": "Editor's choice article",
      "type": "article"
    }
  ]
  